xradios/__about__.py
xradios/__init__.py
xradios/__main__.py
xradios/client.py
xradios/style.css
xradios/ui.md
xradios/ui.py
xradiosd/__about__.py
xradiosd/__init__.py
xradiosd/metadata.py
xradiosd/player.py
xradiosd/server.py
xradiosd/plugins/__init__.py
xradiosd/plugins/plug_1_fm_amsterdam_trance_radio.py
xradiosd/plugins/plug_bbc_radio_1.py
xradiosd/plugins/stream.py
xradios-0.2.0.dist-info/METADATA
xradios-0.2.0.dist-info/WHEEL
xradios-0.2.0.dist-info/entry_points.txt
xradios-0.2.0.dist-info/RECORD
