Metadata-Version: 2.4
Name: xradios
Version: 0.2.0
Summary: Search, bookmark, and stream internet radio stations
Author-email: "André P. Santos" <andreztz@gmail.com>
Requires-Python: >=3.11
Requires-Dist: appdirs>=1.4.4
Requires-Dist: click>=8.1.8
Requires-Dist: cmd-parser>=0.0.1
Requires-Dist: jsonrpclib-pelix>=0.4.3.4
Requires-Dist: pluginbase>=1.0.1
Requires-Dist: pyradios>=2.1.1
Requires-Dist: python-mpv>=1.0.7
Requires-Dist: streamscrobbler3>=0.0.4
Requires-Dist: textual>=3.1.0
Requires-Dist: tinydb>=4.8.2
